thm/main.py
thm/scripts.sh
thm-0.1.0.dist-info/WHEEL
thm-0.1.0.dist-info/METADATA
thm-0.1.0.dist-info/RECORD
