Metadata-Version: 2.1
Name: thm
Version: 0.1.0
Summary: Automatic script downloads & note uploads for TryHackMe's Kali
License: MIT
Author: Your Name
Author-email: you@example.com
Requires-Python: >=3.5,<4.0
Classifier: License :: OSI Approved :: MIT License
Classifier: Programming Language :: Python :: 3
Classifier: Programming Language :: Python :: 3.5
Classifier: Programming Language :: Python :: 3.6
Classifier: Programming Language :: Python :: 3.7
Classifier: Programming Language :: Python :: 3.8
Requires-Dist: click (>=7.1.2,<8.0.0)
